pynams/__init__.py
pynams/blocks.py
pynams/experiments.py
pynams/profiles.py
pynams/pynams.py
pynams/samples.py
pynams/spectra.py
pynams/styles.py
pynams/diffusion/__init__.py
pynams/diffusion/diffusivities.py
pynams/diffusion/literaturevalues.csv
pynams/diffusion/literaturevalues.py
pynams/diffusion/models.py
pynams/example_FTIR_spectra/__init__.py
pynams-0.2.4.dist-info/LICENSE
pynams-0.2.4.dist-info/METADATA
pynams-0.2.4.dist-info/WHEEL
pynams-0.2.4.dist-info/top_level.txt
pynams-0.2.4.dist-info/RECORD
